README.md
setup.cfg
setup.py
moonmask/__init__.py
moonmask/collage.py
moonmask/collage_generator.py
moonmask/custom_image.py
moonmask/jupyter_ui.py
moonmask/mask.py
moonmask/moon_image.py
moonmask/terminal_ui.py
moonmask.egg-info/PKG-INFO
moonmask.egg-info/SOURCES.txt
moonmask.egg-info/dependency_links.txt
moonmask.egg-info/requires.txt
moonmask.egg-info/top_level.txt
moonmask/res/__init__.py
moonmask/res/ascii_art.py
moonmask/res/constants.py